{
  "TranslationProperties": {
    "Name": "server.items.Furniture_Ventilation_Grille.name"
  },
  "Icon": "Icons/ItemsGenerated/Furniture_Ventilation_Grille.png",
  "Categories": [
    "Blocks.Deco",
    "CarpenterProtocolCategory.Deco"
  ],
  "BlockType": {
    "Material": "Solid",
    "DrawType": "Model",
    "Opacity": "Transparent",
    "CustomModel": "Blocks/Decorative_Sets/Cyber/Ventilation/Ventilation_Grille.blockymodel",
    "CustomModelTexture": [
      {
        "Weight": 1,
        "Texture": "Blocks/Decorative_Sets/Cyber/Ventilation/Ventilation_Grille_Texture.png"
      }
    ],
    "CustomModelScale": 1,
    "HitboxType": "Painting",
    "VariantRotation": "NESW",
    "Gathering": {
      "Soft": {}
    },
    "BlockParticleSetId": "Metal",
    "BlockSoundSetId": "Metal",
    "Support": {
      "North": [
        {
          "FaceType": "Full"
        }
      ]
    },
    "ParticleColor": "#a0a0a0",
    "Looping": false
  },
  "PlayerAnimationsId": "Block",
  "IconProperties": {
    "Scale": 0.5,
    "Rotation": [
      351,
      24,
      360
    ],
    "Translation": [
      8,
      -15
    ]
  },
  "Tags": {
    "Type": [
      "Furniture"
    ],
    "Family": [
      "Village"
    ]
  },
  "ItemSoundSetId": "ISS_Items_Metal",
  "Set": "Furniture_Cyber"
}
